dbmi_client/__init__.py
dbmi_client/admin.py
dbmi_client/apps.py
dbmi_client/auth.py
dbmi_client/authn.py
dbmi_client/authz.py
dbmi_client/environment.py
dbmi_client/fileservice.py
dbmi_client/logging.py
dbmi_client/middleware.py
dbmi_client/models.py
dbmi_client/reg.py
dbmi_client/reporting.py
dbmi_client/serializers.py
dbmi_client/settings.py
dbmi_client/support.py
dbmi_client/tests.py
dbmi_client/views.py
dbmi_client/login/__init__.py
dbmi_client/login/apps.py
dbmi_client/login/urls.py
dbmi_client/login/views.py
dbmi_client/migrations/__init__.py
dbmi_client/provider/__init__.py
dbmi_client/provider/auth0.py
dbmi_client/provider/cognito.py
dbmi_client/provider/provider.py
dbmi_client/static/dbmi_client/login/css/style.css
dbmi_client/static/dbmi_client/login/favicon/android-chrome-192x192.png
dbmi_client/static/dbmi_client/login/favicon/android-chrome-256x256.png
dbmi_client/static/dbmi_client/login/favicon/android-chrome-512x512.png
dbmi_client/static/dbmi_client/login/favicon/apple-touch-icon-120x120-precomposed.png
dbmi_client/static/dbmi_client/login/favicon/apple-touch-icon-120x120.png
dbmi_client/static/dbmi_client/login/favicon/apple-touch-icon-152x152-precomposed.png
dbmi_client/static/dbmi_client/login/favicon/apple-touch-icon-152x152.png
dbmi_client/static/dbmi_client/login/favicon/apple-touch-icon-180x180-precomposed.png
dbmi_client/static/dbmi_client/login/favicon/apple-touch-icon-180x180.png
dbmi_client/static/dbmi_client/login/favicon/apple-touch-icon-60x60-precomposed.png
dbmi_client/static/dbmi_client/login/favicon/apple-touch-icon-60x60.png
dbmi_client/static/dbmi_client/login/favicon/apple-touch-icon-76x76-precomposed.png
dbmi_client/static/dbmi_client/login/favicon/apple-touch-icon-76x76.png
dbmi_client/static/dbmi_client/login/favicon/apple-touch-icon-precomposed.png
dbmi_client/static/dbmi_client/login/favicon/apple-touch-icon.png
dbmi_client/static/dbmi_client/login/favicon/favicon-16x16.png
django_dbmi_client-2.4.1.dist-info/METADATA
django_dbmi_client-2.4.1.dist-info/WHEEL
django_dbmi_client-2.4.1.dist-info/top_level.txt
django_dbmi_client-2.4.1.dist-info/RECORD
