Metadata-Version: 2.1
Name: django-dbmi-client
Version: 2.4.1
Home-page: https://github.com/hms-dbmi/django-dbmi-client
Author: HMS DBMI Tech-core
Author-email: dbmi-tech-core@hms.harvard.edu
License: Creative Commons Attribution-Noncommercial-Share Alike license
Classifier: Environment :: Web Environment
Classifier: Framework :: Django
Classifier: Framework :: Django :: 4.2
Classifier: Intended Audience :: Developers
Classifier: License :: OSI Approved :: BSD License
Classifier: Operating System :: OS Independent
Classifier: Programming Language :: Python
Classifier: Programming Language :: Python :: 3
Classifier: Programming Language :: Python :: 3.9
Classifier: Programming Language :: Python :: 3.10
Classifier: Programming Language :: Python :: 3.11
Classifier: Programming Language :: Python :: 3.12
Classifier: Topic :: Internet :: WWW/HTTP
Classifier: Topic :: Internet :: WWW/HTTP :: Dynamic Content
Requires-Dist: django>=2.2
Requires-Dist: djangorestframework>=3.12
Requires-Dist: cryptography>=3.0
Requires-Dist: requests
Requires-Dist: furl
Requires-Dist: pyjwt<3.0,>2.0
Requires-Dist: django-bootstrap3
Requires-Dist: sentry-sdk[django]<3.0
Requires-Dist: pytz
Provides-Extra: dev
Requires-Dist: pre-commit==2.*; extra == "dev"
Provides-Extra: test
Requires-Dist: pytest-django; extra == "test"
Requires-Dist: coverage; extra == "test"
Requires-Dist: mock; extra == "test"
Requires-Dist: responses; extra == "test"
Requires-Dist: django-coverage; extra == "test"
